odoo/addons/test_ssi_multiple_approval_mixin/README.rst
odoo/addons/test_ssi_multiple_approval_mixin/__init__.py
odoo/addons/test_ssi_multiple_approval_mixin/__manifest__.py
odoo/addons/test_ssi_multiple_approval_mixin/models/__init__.py
odoo/addons/test_ssi_multiple_approval_mixin/models/approval_template.py
odoo/addons/test_ssi_multiple_approval_mixin/models/test_multiple_approval_mixin.py
odoo/addons/test_ssi_multiple_approval_mixin/security/ir.model.access.csv
odoo/addons/test_ssi_multiple_approval_mixin/static/description/icon.png
odoo/addons/test_ssi_multiple_approval_mixin/views/test_multiple_approval_view.xml
odoo14_addon_test_ssi_multiple_approval_mixin-14.0.1.1.0.dist-info/METADATA
odoo14_addon_test_ssi_multiple_approval_mixin-14.0.1.1.0.dist-info/WHEEL
odoo14_addon_test_ssi_multiple_approval_mixin-14.0.1.1.0.dist-info/top_level.txt
odoo14_addon_test_ssi_multiple_approval_mixin-14.0.1.1.0.dist-info/RECORD
